grievous/__init__.py
grievous/generalGrievous.py
grievous/GenomicObjects/__init__.py
grievous/GenomicObjects/_utils.py
grievous/GenomicObjects/pvar.py
grievous/GenomicObjects/ssf_tricky.py
grievous/Processes/__init__.py
grievous/Processes/intersect.py
grievous/Processes/merge.py
grievous/Processes/realign.py
grievous/Processes/utils.py
grievous-0.1.5.data/scripts/generalGrievous.py
grievous-0.1.5.dist-info/LICENSE
grievous-0.1.5.dist-info/METADATA
grievous-0.1.5.dist-info/WHEEL
grievous-0.1.5.dist-info/entry_points.txt
grievous-0.1.5.dist-info/top_level.txt
grievous-0.1.5.dist-info/RECORD
