Metadata-Version: 2.1
Name: grievous
Version: 0.1.5
Summary: Generalized Realignment of Innocuous and Essential Variants Otherwise Utilized as Skewed
Home-page: https://github.com/jvtalwar/GRIEVOUS
Author: James V. Talwar
Author-email: jtalwar@ucsd.edu
License: LICENSE
Platform: UNKNOWN
Requires-Python: >=3.7
Requires-Dist: pandas (>=1.3.4)
Requires-Dist: polars (>=0.16.11)
